{
    "5": [
        "zelda",
        "nintendo",
        "motion",
        "development",
        "fantasy",
        "nintendo ead",
        "ead",
        "legend",
        "legend zelda",
        "control nintendo",
        "square",
        "development group",
        "software development",
        "ead software",
        "twilight princess",
        "nintendo imagica",
        "fantasy zelda",
        "imagica digitalscape",
        "digitalscape",
        "zelda motion",
        "zelda twilight",
        "imagica",
        "twilight",
        "princess action",
        "group nintendo",
        "motion control",
        "control",
        "group",
        "software",
        "action fantasy",
        "princess",
        "time",
        "world",
        "magic",
        "save",
        "day",
        "player",
        "fox",
        "day night",
        "night cycle",
        "cycle",
        "night",
        "blur",
        "motion blur",
        "open world",
        "open",
        "quick",
        "quick time",
        "action adventure",
        "point"
    ],
    "3": [
        "zelda",
        "sonic",
        "nintendo",
        "legend zelda",
        "legend",
        "fangame",
        "motion",
        "development",
        "software development",
        "development group",
        "online",
        "group",
        "ead software",
        "fan translation",
        "sonic pc",
        "action unofficial",
        "unofficial fangame",
        "fangame sonic",
        "pc team",
        "translation",
        "sonic hedgehog",
        "unofficial",
        "hedgehog action",
        "pc",
        "software",
        "ead",
        "nintendo ead",
        "translation portuguese",
        "portuguese",
        "portuguese nintendo",
        "group nintendo",
        "connectivity",
        "pack nintendo",
        "protagonist",
        "digitalscape",
        "twilight princess",
        "fantasy zelda",
        "imagica",
        "nintendo imagica",
        "imagica digitalscape",
        "zelda motion",
        "zelda twilight",
        "sword",
        "twilight",
        "nintendo nintendo",
        "princess action",
        "dungeon player",
        "fantasy archery",
        "waker action",
        "aim escaping"
    ],
    "0": [
        "sonic",
        "snk",
        "team",
        "sonic team",
        "screen",
        "enterprise",
        "d4 enterprise",
        "d4",
        "rock music",
        "rock",
        "sonic adventure",
        "sega sonic",
        "playmore",
        "sega",
        "backwards compatibility",
        "backwards",
        "compatibility",
        "playstation",
        "heavy metal",
        "guilty gear",
        "guilty",
        "arc works",
        "works",
        "arc",
        "digital",
        "upgrade",
        "release upgrade",
        "digital distribution",
        "distribution",
        "retroactive",
        "retroactive achievements",
        "metal",
        "action digital",
        "distribution sega",
        "heavy",
        "action martial",
        "virtua tennis",
        "adventure action",
        "wii virtual",
        "anime guitar",
        "title",
        "snk playmore",
        "virtua",
        "playing heavy",
        "metal character",
        "music evo",
        "gear",
        "fighters",
        "king fighters",
        "tennis"
    ],
    "1": [
        "metroid prime",
        "metroid",
        "prime science",
        "advergame nintendo",
        "advergame",
        "fiction advergame",
        "prime",
        "konami",
        "sonic",
        "fiction",
        "science",
        "science fiction",
        "horror konami",
        "castlevania",
        "horror",
        "mega",
        "fantasy horror",
        "snk",
        "score",
        "high score",
        "man",
        "high",
        "screen",
        "sega",
        "playmore",
        "ecclesia",
        "order ecclesia",
        "castlevania order",
        "ecclesia action",
        "mega man",
        "team",
        "playstation",
        "battle",
        "team sega",
        "sonic team",
        "comedy",
        "snk playmore",
        "unofficial",
        "order",
        "king",
        "capcom",
        "stealth",
        "productions",
        "mario",
        "espionage",
        "mascot",
        "kong",
        "screen digital",
        "shared screen",
        "shared"
    ],
    "2": [
        "reader",
        "man",
        "mega man",
        "video",
        "mega",
        "art",
        "fi",
        "wi",
        "wi fi",
        "nintendo wi",
        "robot",
        "play",
        "wii",
        "platforms",
        "game",
        "digital",
        "pixel",
        "mascot",
        "unlockables",
        "playstation",
        "victor",
        "creates",
        "inti",
        "inti creates",
        "retro",
        "animal",
        "stage",
        "management",
        "scrolling",
        "classic",
        "fiction anime",
        "musical industries",
        "jvc musical",
        "jvc",
        "animal crossing",
        "crossing",
        "pixel art",
        "console funcom",
        "soft snk",
        "japan home",
        "home video",
        "aspect",
        "aspect takara",
        "monolith corp",
        "video prisma",
        "mutech",
        "company victor",
        "special action",
        "combat retroachievements",
        "industries hudson"
    ],
    "4": [
        "fantasy",
        "square",
        "namco",
        "development",
        "motion",
        "final fantasy",
        "zelda",
        "final",
        "magic",
        "tales",
        "time",
        "studio",
        "save",
        "action fantasy",
        "xi nexon",
        "nexon",
        "nintendo",
        "fantasy xi",
        "xi",
        "twilight",
        "imagica",
        "twilight princess",
        "zelda motion",
        "imagica digitalscape",
        "digitalscape",
        "zelda twilight",
        "fantasy zelda",
        "nintendo imagica",
        "legend",
        "princess action",
        "warping",
        "quick",
        "quick time",
        "legend zelda",
        "group nintendo",
        "control nintendo",
        "ead software",
        "development group",
        "software development",
        "ead",
        "nintendo ead",
        "poisoning",
        "drama",
        "group",
        "princess",
        "software",
        "leveling",
        "motion blur",
        "blur",
        "magic grinding"
    ],
    "7": [
        "square enix",
        "enix",
        "zelda",
        "kingdom hearts",
        "square",
        "hearts",
        "kingdom",
        "super",
        "control nintendo",
        "imagica",
        "zelda twilight",
        "nintendo imagica",
        "fantasy zelda",
        "twilight princess",
        "imagica digitalscape",
        "digitalscape",
        "zelda motion",
        "twilight",
        "princess action",
        "division",
        "group nintendo",
        "princess",
        "legend zelda",
        "software",
        "legend",
        "development",
        "action fantasy",
        "motion control",
        "ead software",
        "development group",
        "software development",
        "enix business",
        "business division",
        "enix product",
        "group",
        "console",
        "control",
        "nintendo hal",
        "snk",
        "action cast",
        "superscape disney",
        "cast superscape",
        "disney mobile",
        "superscape",
        "cast",
        "nintendo",
        "gamecube retroachievements",
        "business",
        "hearts action",
        "ness special"
    ],
    "6": [
        "nintendo",
        "archery",
        "choice nintendo",
        "mobile",
        "treasure atari",
        "publishing treasure",
        "fiction nicalis",
        "atari zereo",
        "nicalis",
        "nicalis rev",
        "rev entertainment",
        "ikaruga action",
        "ikaruga",
        "zereo",
        "player choice",
        "software publishing",
        "rev",
        "publishing",
        "choice",
        "super",
        "hearts action",
        "nintendo gateway",
        "gateway",
        "entertainment software",
        "bros",
        "atari",
        "disney mobile",
        "action cast",
        "cast",
        "cast superscape",
        "superscape",
        "superscape disney",
        "vivendi games",
        "disney",
        "fairy",
        "hearts",
        "hidden",
        "adventure fairy",
        "game console",
        "pok mon",
        "mon",
        "legendary pok",
        "platform fighting",
        "pikachu",
        "super smash",
        "smash",
        "fighting legendary",
        "smash bros",
        "pok",
        "fantasy"
    ]
}