{
    "2": [
        "nintendo",
        "action",
        "fantasy",
        "square",
        "action fantasy",
        "namco",
        "konami",
        "motion",
        "development",
        "zelda"
    ],
    "7": [
        "nintendo",
        "action",
        "fantasy",
        "sonic",
        "character",
        "game",
        "protagonist",
        "boss",
        "final fantasy",
        "final"
    ],
    "1": [
        "nintendo",
        "action",
        "namco",
        "fantasy",
        "zelda",
        "sonic",
        "action fantasy",
        "boss",
        "tales",
        "protagonist"
    ],
    "4": [
        "nintendo",
        "square",
        "zelda",
        "motion",
        "fantasy",
        "action",
        "development",
        "time",
        "protagonist",
        "save"
    ],
    "8": [
        "nintendo",
        "super",
        "game",
        "boss",
        "protagonist",
        "character",
        "time",
        "square",
        "wii",
        "fantasy"
    ],
    "9": [
        "action",
        "nintendo",
        "character",
        "fantasy",
        "game",
        "sonic",
        "protagonist",
        "boss",
        "action fantasy",
        "capcom"
    ],
    "3": [
        "nintendo",
        "sonic",
        "boss",
        "protagonist",
        "fantasy",
        "game",
        "sega",
        "action fantasy",
        "digital",
        "character"
    ],
    "6": [
        "nintendo",
        "action",
        "square",
        "sonic",
        "fantasy",
        "motion",
        "development",
        "zelda",
        "protagonist",
        "character"
    ],
    "5": [
        "nintendo",
        "sonic",
        "boss",
        "protagonist",
        "character",
        "combat",
        "time",
        "digital",
        "sega",
        "game"
    ],
    "0": [
        "nintendo",
        "action",
        "game",
        "zelda",
        "time",
        "fantasy",
        "boss",
        "nintendo ead",
        "ead",
        "character"
    ]
}